[
    {
        "id": "53983908339b7857",
        "type": "tab",
        "label": "Buy High Dividend Portfolio",
        "disabled": false,
        "info": "",
        "env": []
    },
    {
        "id": "ce542bbb92fa91ad",
        "type": "comment",
        "z": "53983908339b7857",
        "name": "The name of this strategy is \"Buy High Dividend Portfolio\"",
        "info": "",
        "x": 250,
        "y": 40,
        "wires": []
    },
    {
        "id": "b241ed3e3cccf554",
        "type": "comment",
        "z": "53983908339b7857",
        "name": "Flow 1: Set values for portfoio in 'get dividend stocks' and 'define values'",
        "info": "",
        "x": 320,
        "y": 280,
        "wires": []
    },
    {
        "id": "e43f457906461bf6",
        "type": "inject",
        "z": "53983908339b7857",
        "name": "get dividened stocks",
        "props": [
            {
                "p": "topic",
                "vt": "str"
            }
        ],
        "repeat": "",
        "crontab": "",
        "once": false,
        "onceDelay": 0.1,
        "topic": "select distinct ticker from dividends where pct between 11 and 15 and exdate > '2022-10-01' ",
        "x": 190,
        "y": 340,
        "wires": [
            [
                "28bbe2f0fe45b7d3"
            ]
        ]
    },
    {
        "id": "28bbe2f0fe45b7d3",
        "type": "mysql",
        "z": "53983908339b7857",
        "mydb": "3564bcf07c743fdf",
        "name": "ptsapi",
        "x": 350,
        "y": 340,
        "wires": [
            [
                "c5ff0bfed3f4311c"
            ]
        ]
    },
    {
        "id": "c5ff0bfed3f4311c",
        "type": "function",
        "z": "53983908339b7857",
        "name": "get tickers",
        "func": "let tickers = ''\nlet item = 1;\n\nfor (let item of msg.payload) {\n    let ticker = item.ticker;\n    tickers += ticker+ \", \"\n}\n\nmsg.tickers = tickers\nnode.warn(tickers)\nreturn msg;",
        "outputs": 1,
        "noerr": 0,
        "initialize": "",
        "finalize": "",
        "libs": [],
        "x": 490,
        "y": 340,
        "wires": [
            [
                "df8ee43084503af9"
            ]
        ]
    },
    {
        "id": "4e8a8d4476dba87b",
        "type": "comment",
        "z": "53983908339b7857",
        "name": "Flow 1: Define Strategy and Set Trading Values (ONCE)",
        "info": "",
        "x": 260,
        "y": 80,
        "wires": []
    },
    {
        "id": "eabad259bff2717a",
        "type": "function",
        "z": "53983908339b7857",
        "name": "define values required for adding trade to portfolio",
        "func": "// portfolio_id is set to unixtime\nlet d = Date.now() // use to dynamically assign id\n\nlet id = d\nlet login = 'pta17'\nlet ticker = flow.get(\"tickers\")\nlet algo_name = \"High Dividend Stocks (> 11%)\"\nlet asset_class = 'stocks' // stocks or crypto\nlet number = 135 // number of tickers in portfolio\nlet target = 1 // target profit pct\nlet account = 'paper'\nlet psize = 50000 // size of portfolio\nlet status = 'running'\nlet algo_type = 'interday'\nlet benchmark = 'SPY'\n\nmsg.id = id\nmsg.login = login\nmsg.ticker = ticker\nmsg.algo_name = algo_name\nmsg.asset_class = asset_class\nmsg.number = number\nmsg.target = target\nmsg.account = account\nmsg.psize = psize\nmsg.status = status\nmsg.algo_type = algo_type\nmsg.benchmark = benchmark\n\nreturn msg;",
        "outputs": 1,
        "noerr": 0,
        "initialize": "",
        "finalize": "",
        "libs": [],
        "x": 450,
        "y": 200,
        "wires": [
            [
                "c5b162c3cd613d62"
            ]
        ]
    },
    {
        "id": "075aca29838fe3d0",
        "type": "inject",
        "z": "53983908339b7857",
        "name": "GO",
        "props": [],
        "repeat": "3600",
        "crontab": "",
        "once": false,
        "onceDelay": 0.1,
        "topic": "",
        "x": 190,
        "y": 200,
        "wires": [
            [
                "eabad259bff2717a"
            ]
        ]
    },
    {
        "id": "c5b162c3cd613d62",
        "type": "change",
        "z": "53983908339b7857",
        "name": "store as flow vars",
        "rules": [
            {
                "t": "set",
                "p": "id",
                "pt": "flow",
                "to": "id",
                "tot": "msg"
            },
            {
                "t": "set",
                "p": "login",
                "pt": "flow",
                "to": "login",
                "tot": "msg"
            },
            {
                "t": "set",
                "p": "account",
                "pt": "flow",
                "to": "account",
                "tot": "msg"
            },
            {
                "t": "set",
                "p": "ticker",
                "pt": "flow",
                "to": "ticker",
                "tot": "msg"
            },
            {
                "t": "set",
                "p": "algo_name",
                "pt": "flow",
                "to": "algo_name",
                "tot": "msg"
            },
            {
                "t": "set",
                "p": "asset_class",
                "pt": "flow",
                "to": "asset_class",
                "tot": "msg"
            },
            {
                "t": "set",
                "p": "number",
                "pt": "flow",
                "to": "number",
                "tot": "msg"
            },
            {
                "t": "set",
                "p": "psize",
                "pt": "flow",
                "to": "psize",
                "tot": "msg"
            },
            {
                "t": "set",
                "p": "status",
                "pt": "flow",
                "to": "status",
                "tot": "msg"
            },
            {
                "t": "set",
                "p": "algo_type",
                "pt": "flow",
                "to": "algo_type",
                "tot": "msg"
            },
            {
                "t": "set",
                "p": "benchmark",
                "pt": "flow",
                "to": "benchmark",
                "tot": "msg"
            },
            {
                "t": "set",
                "p": "target",
                "pt": "flow",
                "to": "target",
                "tot": "msg"
            }
        ],
        "action": "",
        "property": "",
        "from": "",
        "to": "",
        "reg": false,
        "x": 770,
        "y": 200,
        "wires": [
            []
        ]
    },
    {
        "id": "5cb9d0956b48a4cb",
        "type": "comment",
        "z": "53983908339b7857",
        "name": "Flow 3: Create new entry in algos table (ONCE)",
        "info": "",
        "x": 220,
        "y": 580,
        "wires": []
    },
    {
        "id": "e398886e06b6190d",
        "type": "function",
        "z": "53983908339b7857",
        "name": "add values to algos table",
        "func": "let login = flow.get(\"login\")\nlet id = flow.get(\"id\")\nlet algo_name = flow.get(\"algo_name\")\nlet algo_type = flow.get(\"algo_type\")\nlet status = flow.get(\"status\")\nlet portfolio_size = flow.get(\"psize\")\nlet benchmark = flow.get(\"benchmark\")\nlet benchmark_start = global.get(\"spy_current\")\n\nmsg.query = \"insert into algos (login,id,algo_name,algo_type,status,portfolio_size,benchmark,benchmark_start) values ('\" + login + \"','\" +id+ \"','\" +algo_name+ \"','\" +algo_type+ \"','\" +status+ \"','\" +portfolio_size+ \"','\" +benchmark+ \"','\" +benchmark_start+ \"');\"\nnode.warn(msg.query)\nreturn msg;",
        "outputs": 1,
        "noerr": 0,
        "initialize": "",
        "finalize": "",
        "libs": [],
        "x": 410,
        "y": 640,
        "wires": [
            [
                "745a55ad824cc878"
            ]
        ]
    },
    {
        "id": "745a55ad824cc878",
        "type": "postgresql",
        "z": "53983908339b7857",
        "name": "postgres",
        "query": "",
        "postgreSQLConfig": "7455395cf269fb2b",
        "split": false,
        "rowsPerMsg": 1,
        "outputs": 1,
        "x": 600,
        "y": 640,
        "wires": [
            []
        ]
    },
    {
        "id": "4b8b27b879633c63",
        "type": "inject",
        "z": "53983908339b7857",
        "name": "GO",
        "props": [],
        "repeat": "",
        "crontab": "",
        "once": false,
        "onceDelay": 0.1,
        "topic": "",
        "x": 230,
        "y": 640,
        "wires": [
            [
                "e398886e06b6190d"
            ]
        ]
    },
    {
        "id": "a1a4af68a1e6e445",
        "type": "comment",
        "z": "53983908339b7857",
        "name": "Flow 4: Create trading flow (ONCE)",
        "info": "",
        "x": 200,
        "y": 720,
        "wires": []
    },
    {
        "id": "7cb1c5d4e56cf2f9",
        "type": "inject",
        "z": "53983908339b7857",
        "name": "Display Algos",
        "props": [
            {
                "p": "query",
                "v": "select * from algos",
                "vt": "str"
            },
            {
                "p": "query1",
                "v": "delete from algos where id = 1671644577762",
                "vt": "str"
            },
            {
                "p": "query2",
                "v": "update algos set login = 'pta19'",
                "vt": "str"
            },
            {
                "p": "query1",
                "v": "update algos set gain_today = -158.7135149876422767159823658, gain_alltime = -158.71351498764227674, pctgain_today = 0, pctgain_alltime = 0 where algo_name = 'Buy and Sell BTCUSD on Profit Target';",
                "vt": "str"
            },
            {
                "p": "query1",
                "v": "select * from order_confirms",
                "vt": "str"
            },
            {
                "p": "query1",
                "v": "update order_confirms set subtag = 'Buy/Short SPY on News' where symbol = 'SPY'",
                "vt": "str"
            },
            {
                "p": "query1",
                "v": "update order_confirms set subtag = 'Trade BTCUSD'  where symbol = 'BTC/USD'",
                "vt": "str"
            }
        ],
        "repeat": "",
        "crontab": "",
        "once": false,
        "onceDelay": 0.1,
        "topic": "",
        "x": 810,
        "y": 640,
        "wires": [
            [
                "07b034ec38db4f3a"
            ]
        ]
    },
    {
        "id": "07b034ec38db4f3a",
        "type": "postgresql",
        "z": "53983908339b7857",
        "name": "postgres",
        "query": "",
        "postgreSQLConfig": "7455395cf269fb2b",
        "split": false,
        "rowsPerMsg": 1,
        "outputs": 1,
        "x": 960,
        "y": 640,
        "wires": [
            [
                "d8b08714a2a9462c"
            ]
        ]
    },
    {
        "id": "d8b08714a2a9462c",
        "type": "debug",
        "z": "53983908339b7857",
        "name": "debug 219",
        "active": true,
        "tosidebar": true,
        "console": false,
        "tostatus": false,
        "complete": "false",
        "statusVal": "",
        "statusType": "auto",
        "x": 1110,
        "y": 640,
        "wires": []
    },
    {
        "id": "cbd1346e2184821c",
        "type": "function",
        "z": "53983908339b7857",
        "name": "get list of tickers to buy",
        "func": "let ticker = flow.get(\"tickers\")\nmsg.payload = ticker\nreturn msg;",
        "outputs": 1,
        "noerr": 0,
        "initialize": "",
        "finalize": "",
        "libs": [],
        "x": 330,
        "y": 780,
        "wires": [
            [
                "5fc2b5542efecd0e"
            ]
        ]
    },
    {
        "id": "5fc2b5542efecd0e",
        "type": "split",
        "z": "53983908339b7857",
        "name": "",
        "splt": ",",
        "spltType": "str",
        "arraySplt": 1,
        "arraySpltType": "len",
        "stream": false,
        "addname": "",
        "x": 530,
        "y": 780,
        "wires": [
            [
                "d2e0e8107ef5919d"
            ]
        ]
    },
    {
        "id": "14fba4d9e603b640",
        "type": "function",
        "z": "53983908339b7857",
        "name": "get list of tickers to buy",
        "func": "let id = msg.id\nlet symbol = msg.payload\nsymbol = symbol.replace(\" \",\"\")\nmsg.query = \"select polygon_symbol, alpaca_symbol from alpaca_assets where symbol = '\" +symbol+ \"';\"\n//node.warn(msg.query)\nmsg.symbol = symbol\nreturn msg;",
        "outputs": 1,
        "noerr": 0,
        "initialize": "",
        "finalize": "",
        "libs": [],
        "x": 870,
        "y": 780,
        "wires": [
            [
                "494b1903b9952845"
            ]
        ]
    },
    {
        "id": "1ebb380c41bb60f6",
        "type": "function-npm",
        "z": "53983908339b7857",
        "name": "Get price of trade trade",
        "func": "let symbol = msg.polygon_symbol\n\nlet cnt = 1 // gets last trade\n\n/* Setup polygon request arguments */\nmsg.payload = {\n    symbol: symbol,\n    cnt: cnt,\n}\n\n\n//node.warn(symbol)\nnode.warn(msg.payload)\n\nreturn msg;",
        "outputs": 1,
        "noerr": 0,
        "x": 690,
        "y": 840,
        "wires": [
            [
                "19adb054872275ba"
            ]
        ]
    },
    {
        "id": "d2e0e8107ef5919d",
        "type": "delay",
        "z": "53983908339b7857",
        "name": "",
        "pauseType": "rate",
        "timeout": "1",
        "timeoutUnits": "seconds",
        "rate": "1",
        "nbRateUnits": "1",
        "rateUnits": "second",
        "randomFirst": "1",
        "randomLast": "5",
        "randomUnits": "seconds",
        "drop": false,
        "allowrate": false,
        "outputs": 1,
        "x": 670,
        "y": 780,
        "wires": [
            [
                "14fba4d9e603b640"
            ]
        ]
    },
    {
        "id": "729b04292eb5306e",
        "type": "function",
        "z": "53983908339b7857",
        "name": "get symbols from alpaca_assets",
        "func": "let polygon_symbol = msg.payload[\"polygon_symbol\"]\nlet alpaca_symbol = msg.payload[\"alpaca_symbol\"]\nlet symbol = msg.symbol\n\nmsg.alpaca_symbol = alpaca_symbol\nmsg.polygon_symbol = polygon_symbol\nmsg.symbol = symbol\n//node.warn(\"Symbol: \" +symbol+ \" Polygon Symbol:\" +polygon_symbol+ \" Alpaca Symbol: \" +alpaca_symbol) \nreturn msg;",
        "outputs": 1,
        "noerr": 0,
        "initialize": "",
        "finalize": "",
        "libs": [],
        "x": 430,
        "y": 840,
        "wires": [
            [
                "1ebb380c41bb60f6"
            ]
        ]
    },
    {
        "id": "494b1903b9952845",
        "type": "postgresql",
        "z": "53983908339b7857",
        "name": "postgres",
        "query": "",
        "postgreSQLConfig": "7455395cf269fb2b",
        "split": false,
        "rowsPerMsg": 1,
        "outputs": 1,
        "x": 1080,
        "y": 780,
        "wires": [
            [
                "c27bac568662c534"
            ]
        ]
    },
    {
        "id": "c27bac568662c534",
        "type": "split",
        "z": "53983908339b7857",
        "name": "",
        "splt": ",",
        "spltType": "str",
        "arraySplt": 1,
        "arraySpltType": "len",
        "stream": false,
        "addname": "",
        "x": 230,
        "y": 840,
        "wires": [
            [
                "729b04292eb5306e"
            ]
        ]
    },
    {
        "id": "cfb1ddc4c5e08e0a",
        "type": "inject",
        "z": "53983908339b7857",
        "name": "GO",
        "props": [],
        "repeat": "",
        "crontab": "",
        "once": false,
        "onceDelay": 0.1,
        "topic": "",
        "x": 130,
        "y": 780,
        "wires": [
            [
                "cbd1346e2184821c",
                "033a6c1ea8aea3c9"
            ]
        ]
    },
    {
        "id": "be919c9fe226c864",
        "type": "function",
        "z": "53983908339b7857",
        "name": " last trade",
        "func": "let price = 0\nlet item = 0\n\n\nfor (item of msg.payload.results) {\n    price = item.price;\n    \n}\n\nprice = price.toFixed(2)\nmsg.price = price\n//node.warn(price)\nreturn msg;",
        "outputs": 1,
        "noerr": 0,
        "initialize": "",
        "finalize": "",
        "libs": [],
        "x": 1140,
        "y": 840,
        "wires": [
            [
                "3e6d59eb28fae0e5"
            ]
        ]
    },
    {
        "id": "19adb054872275ba",
        "type": "polygon-last-trade-v3",
        "z": "53983908339b7857",
        "conf": "651f0aab10dc1632",
        "symbol": "",
        "x": 940,
        "y": 840,
        "wires": [
            [
                "be919c9fe226c864"
            ]
        ]
    },
    {
        "id": "3e6d59eb28fae0e5",
        "type": "function",
        "z": "53983908339b7857",
        "name": "create Alpaca order ",
        "func": "let ticker = msg.symbol\n//let ticker = msg.alpaca_symbol\nlet algo_name = flow.get(\"algo_name\")\nlet number = flow.get(\"number\")\nlet psize = flow.get(\"psize\")\nlet price = msg.price\n\nlet qty = ((psize / number) / price)\nqty = qty.toFixed(0) // round to whole numbers for limit trades\n\n// create a unique clientid with unixtime\nlet d = Date.now()\nlet client_order_id = ticker + d\nmsg.clientorderid = client_order_id // passes this variable in the flow \n\n\nlet subtag = algo_name\n\n// create a order for Alpaca\nlet temp = ''\ntemp = {\n    \"symbol\": ticker,\n    \"qty\": qty,\n    \"side\": 'buy',\n    \"type\": 'limit',\n    \"limit_price\": price, \n    \"client_order_id\": client_order_id,\n//    \"subtag\": subtag,\n    \"time_in_force\": \"day\"\n};\n\nmsg.payload = temp\nnode.warn(msg.payload)\n\nreturn msg;\n",
        "outputs": 1,
        "noerr": 0,
        "initialize": "",
        "finalize": "",
        "libs": [],
        "x": 370,
        "y": 900,
        "wires": [
            [
                "5ec872bdcfdbba29"
            ]
        ]
    },
    {
        "id": "5ec872bdcfdbba29",
        "type": "alpaca-order",
        "z": "53983908339b7857",
        "conf": "e535f42f1df1b25f",
        "x": 590,
        "y": 900,
        "wires": [
            [
                "56e9484fc851b0aa"
            ]
        ]
    },
    {
        "id": "bc2f31d2a060eebe",
        "type": "postgresql",
        "z": "53983908339b7857",
        "name": "postgres",
        "query": "",
        "postgreSQLConfig": "7455395cf269fb2b",
        "split": false,
        "rowsPerMsg": 1,
        "outputs": 1,
        "x": 1060,
        "y": 900,
        "wires": [
            []
        ]
    },
    {
        "id": "56e9484fc851b0aa",
        "type": "function",
        "z": "53983908339b7857",
        "name": "insert into order_confirms table",
        "func": "let id = msg.payload[\"id\"]\nlet client_order_id = msg.payload[\"client_order_id\"]\nlet created_at = msg.payload[\"created_at\"]\nlet updated_at = msg.payload[\"updated_at\"]\nlet submitted_at = msg.payload[\"submitted_at\"]\nlet filled_at = msg.payload[\"filled_at\"]\nlet expired_at = msg.payload[\"expired_at\"]\nlet canceled_at = msg.payload[\"canceled_at\"]\nlet failed_at = msg.payload[\"failed_at\"]\nlet replaced_at = msg.payload[\"replaced_at\"]\nlet replaced_by = msg.payload[\"replaced_by\"]\nlet replaces = msg.payload[\"replaces\"]\nlet asset_id = msg.payload[\"asset_id\"]\nlet symbol = msg.payload[\"symbol\"]\nlet asset_class = msg.payload[\"asset_class\"]\nlet notional = msg.payload[\"notional\"]\nlet qty = msg.payload[\"qty\"]\nlet filled_qty = msg.payload[\"filled_qty\"]\nlet filled_avg_price = msg.payload[\"filled_avg_price\"]\nlet order_class = msg.payload[\"order_class\"]\nlet order_type = msg.payload[\"order_type\"]\nlet type = msg.payload[\"type\"]\nlet side = msg.payload[\"side\"]\nlet time_in_force = msg.payload[\"time_in_force\"]\nlet limit_price = msg.payload[\"limit_price\"]\nlet stop_price = msg.payload[\"stop_price\"]\nlet status = msg.payload[\"status\"]\nlet extended_hours = msg.payload[\"extended_hours\"]\nlet legs = msg.payload[\"legs\"]\nlet trail_percent = msg.payload[\"trail_percent\"]\nlet trail_price = msg.payload[\"trail_price\"]\nlet hwm = msg.payload[\"hwm\"]\nlet subtag = msg.payload[\"subtag\"]\nlet source = msg.payload[\"source\"]\n\nsubtag = flow.get(\"algo_name\")\n\nlet result = symbol.includes(\"/\");\nif (result == true) {\n    symbol = symbol.replace(\"/\",\"\")\n}\n\nlet sql = \"insert into order_confirms(id, client_order_id, created_at, updated_at, submitted_at, asset_id, symbol, asset_class, qty, order_type, type, side, time_in_force, status, subtag, source,extended_hours) values \"\nsql += \"('\" + id + \"', '\" + client_order_id + \"', '\" + created_at + \"', '\" + updated_at + \"', '\" + submitted_at + \"', '\" + asset_id + \"', '\" + symbol + \"', '\" + asset_class + \"', '\" + qty + \"', '\" + order_type + \"', '\" + type + \"', '\" + side + \"', '\" + time_in_force + \"', '\" + status + \"', '\" + subtag + \"', '\" + source + \"', '\" + extended_hours+ \"'); \" \n\nmsg.query = sql\nnode.warn(msg.query)\n\nreturn msg;",
        "outputs": 1,
        "noerr": 0,
        "initialize": "",
        "finalize": "",
        "libs": [],
        "x": 830,
        "y": 900,
        "wires": [
            [
                "bc2f31d2a060eebe"
            ]
        ]
    },
    {
        "id": "ef76c2a9391f24d9",
        "type": "split",
        "z": "53983908339b7857",
        "name": "",
        "splt": "\\n",
        "spltType": "str",
        "arraySplt": 1,
        "arraySpltType": "len",
        "stream": false,
        "addname": "",
        "x": 870,
        "y": 980,
        "wires": [
            [
                "3caf0eba9654f7bf"
            ]
        ]
    },
    {
        "id": "280c0ff31244dd97",
        "type": "alpaca-query-order",
        "z": "53983908339b7857",
        "conf": "e535f42f1df1b25f",
        "x": 700,
        "y": 980,
        "wires": [
            [
                "ef76c2a9391f24d9"
            ]
        ]
    },
    {
        "id": "6de463d1e8ff3c74",
        "type": "function",
        "z": "53983908339b7857",
        "name": "get last closed order paper",
        "func": "/* Get Flow variables */\n\nlet ordertype = flow.get(\"orders\")\n//let limit  = flow.get(\"cnt\")\nordertype = \"closed\"\n\n/* Setup alpaca request arguments */\n\nmsg.payload = {\n    status: ordertype, // \"open or closed\"\n    limit: \"20\", // default is 500\n\tdirection: \"desc\" //  \"asc or desc\"\n\n}\n\n//node.warn(msg.payload)\n\nreturn msg;",
        "outputs": 1,
        "noerr": 0,
        "initialize": "",
        "finalize": "",
        "libs": [],
        "x": 440,
        "y": 980,
        "wires": [
            [
                "280c0ff31244dd97"
            ]
        ]
    },
    {
        "id": "3caf0eba9654f7bf",
        "type": "function",
        "z": "53983908339b7857",
        "name": "update orders confirms",
        "func": "\n\nlet id = msg.payload[\"id\"]\nlet client_order_id = msg.payload[\"client_order_id\"]\nlet created_at = msg.payload[\"created_at\"]\nlet updated_at = msg.payload[\"updated_at\"]\nlet submitted_at = msg.payload[\"submitted_at\"]\nlet filled_at = msg.payload[\"filled_at\"]\nlet expired_at = msg.payload[\"expired_at\"]\nlet canceled_at = msg.payload[\"canceled_at\"]\nlet failed_at = msg.payload[\"failed_at\"]\nlet replaced_at = msg.payload[\"replaced_at\"]\nlet replaced_by = msg.payload[\"replaced_by\"]\nlet replaces = msg.payload[\"replaces\"]\nlet asset_id = msg.payload[\"asset_id\"]\nlet symbol = msg.payload[\"symbol\"]\nlet asset_class = msg.payload[\"asset_class\"]\nlet notional = msg.payload[\"notional\"]\nlet qty = msg.payload[\"qty\"]\nif (qty === null) { qty = 0 }\n\nlet filled_qty = msg.payload[\"filled_qty\"]\nif (filled_qty === null) { filled_qty = 0 }\n\nlet filled_avg_price = msg.payload[\"filled_avg_price\"]\nif (filled_avg_price === null) { filled_avg_price = 0 }\n\nlet order_class = msg.payload[\"order_class\"]\nlet order_type = msg.payload[\"order_type\"]\nlet type = msg.payload[\"type\"]\nlet side = msg.payload[\"side\"]\nlet time_in_force = msg.payload[\"time_in_force\"]\n\nlet limit_price = msg.payload[\"limit_price\"]\nif (limit_price === null) { limit_price = 0 }\n\nlet stop_price = msg.payload[\"stop_price\"]\nif (stop_price === null ){ stop_price = 0}\n\nlet status = msg.payload[\"status\"]\nlet extended_hours = msg.payload[\"extended_hours\"]\nlet legs = msg.payload[\"legs\"]\n\nlet trail_percent = msg.payload[\"trail_percent\"]\nif (trail_percent === null) { trail_percent = 0 }\n\nlet trail_price = msg.payload[\"trail_price\"]\nif (trail_price === null) { trail_price = 0 }\n\nlet hwm = msg.payload[\"hwm\"]\nlet source = msg.payload[\"source\"]\nlet subtag = flow.get(\"algo_name\")\n\n\nmsg.query = \"update order_confirms set filled_at = '\" + filled_at + \"', filled_qty = '\" + filled_qty + \"', filled_avg_price = '\" + filled_avg_price + \"', limit_price = '\" + limit_price + \"', status = '\" + status + \"', subtag = '\" + subtag+ \"', source = '\" + source + \"', extended_hours = '\" + extended_hours+ \"' where id = '\" +id+ \"';\"\nnode.warn(msg.query)\nreturn msg;",
        "outputs": 1,
        "noerr": 0,
        "initialize": "",
        "finalize": "",
        "libs": [],
        "x": 450,
        "y": 1040,
        "wires": [
            [
                "9d3bf3e50de02228"
            ]
        ]
    },
    {
        "id": "9d3bf3e50de02228",
        "type": "postgresql",
        "z": "53983908339b7857",
        "name": "postgres",
        "query": "",
        "postgreSQLConfig": "7455395cf269fb2b",
        "split": false,
        "rowsPerMsg": 1,
        "outputs": 1,
        "x": 640,
        "y": 1040,
        "wires": [
            []
        ]
    },
    {
        "id": "033a6c1ea8aea3c9",
        "type": "delay",
        "z": "53983908339b7857",
        "name": "",
        "pauseType": "delay",
        "timeout": "10",
        "timeoutUnits": "minutes",
        "rate": "1",
        "nbRateUnits": "1",
        "rateUnits": "second",
        "randomFirst": "1",
        "randomLast": "5",
        "randomUnits": "seconds",
        "drop": false,
        "allowrate": false,
        "outputs": 1,
        "x": 210,
        "y": 980,
        "wires": [
            [
                "6de463d1e8ff3c74"
            ]
        ]
    },
    {
        "id": "df8ee43084503af9",
        "type": "change",
        "z": "53983908339b7857",
        "name": "",
        "rules": [
            {
                "t": "set",
                "p": "tickers",
                "pt": "flow",
                "to": "tickers",
                "tot": "msg"
            }
        ],
        "action": "",
        "property": "",
        "from": "",
        "to": "",
        "reg": false,
        "x": 660,
        "y": 340,
        "wires": [
            [
                "cd4e354f5b970196",
                "b218797edc086639"
            ]
        ]
    },
    {
        "id": "cd4e354f5b970196",
        "type": "function",
        "z": "53983908339b7857",
        "name": "get tickers ",
        "func": "let ticker = msg.tickers\nmsg.payload = ticker\nreturn msg;",
        "outputs": 1,
        "noerr": 0,
        "initialize": "",
        "finalize": "",
        "libs": [],
        "x": 830,
        "y": 340,
        "wires": [
            [
                "cae9419796c77c72"
            ]
        ]
    },
    {
        "id": "cae9419796c77c72",
        "type": "split",
        "z": "53983908339b7857",
        "name": "",
        "splt": ",",
        "spltType": "str",
        "arraySplt": 1,
        "arraySpltType": "len",
        "stream": false,
        "addname": "",
        "x": 970,
        "y": 340,
        "wires": [
            [
                "cecccdd7ee710621"
            ]
        ]
    },
    {
        "id": "cecccdd7ee710621",
        "type": "function",
        "z": "53983908339b7857",
        "name": "insert into tickers",
        "func": "let id = flow.get(\"id\")\nlet symbol = msg.payload\nlet portfolioname = flow.get(\"algo_name\")\nsymbol = symbol.replace(\" \",\"\")\n//msg.query = \"delete from tickers where symbol = '\" + symbol + \"';\"\nmsg.query = \"insert into tickers (id, symbol, portfolioname) values (\" +id+ \",'\" + symbol + \"', '\" +portfolioname + \"');\"\nnode.warn(msg.query)\nmsg.symbol = symbol\nreturn msg;",
        "outputs": 1,
        "noerr": 0,
        "initialize": "",
        "finalize": "",
        "libs": [],
        "x": 1130,
        "y": 340,
        "wires": [
            [
                "eb8e0f908e5fae9c"
            ]
        ]
    },
    {
        "id": "eb8e0f908e5fae9c",
        "type": "postgresql",
        "z": "53983908339b7857",
        "name": "postgres",
        "query": "",
        "postgreSQLConfig": "7455395cf269fb2b",
        "split": false,
        "rowsPerMsg": 1,
        "outputs": 1,
        "x": 1300,
        "y": 340,
        "wires": [
            []
        ]
    },
    {
        "id": "bbde9050530fb5dd",
        "type": "function",
        "z": "53983908339b7857",
        "name": "get tickers with name from alpaca_assets",
        "func": "msg.query = \"update tickers set name = alpaca_assets.name FROM alpaca_assets where alpaca_assets.symbol = tickers.symbol\"\nnode.warn(msg.query)\nreturn msg;\n",
        "outputs": 1,
        "noerr": 0,
        "initialize": "",
        "finalize": "",
        "libs": [],
        "x": 1060,
        "y": 380,
        "wires": [
            [
                "5a96d67ba119dd89"
            ]
        ]
    },
    {
        "id": "b218797edc086639",
        "type": "delay",
        "z": "53983908339b7857",
        "name": "",
        "pauseType": "delay",
        "timeout": "5",
        "timeoutUnits": "seconds",
        "rate": "1",
        "nbRateUnits": "1",
        "rateUnits": "second",
        "randomFirst": "1",
        "randomLast": "5",
        "randomUnits": "seconds",
        "drop": false,
        "allowrate": false,
        "outputs": 1,
        "x": 820,
        "y": 380,
        "wires": [
            [
                "bbde9050530fb5dd"
            ]
        ]
    },
    {
        "id": "5a96d67ba119dd89",
        "type": "postgresql",
        "z": "53983908339b7857",
        "name": "postgres",
        "query": "",
        "postgreSQLConfig": "7455395cf269fb2b",
        "split": false,
        "rowsPerMsg": 1,
        "outputs": 1,
        "x": 1300,
        "y": 380,
        "wires": [
            []
        ]
    },
    {
        "id": "125938de7838363c",
        "type": "inject",
        "z": "53983908339b7857",
        "name": "get dividened stocks",
        "props": [
            {
                "p": "topic",
                "vt": "str"
            }
        ],
        "repeat": "",
        "crontab": "",
        "once": false,
        "onceDelay": 0.1,
        "topic": "select distinct ticker from dividends where pct between 11 and 15 and exdate > '2022-10-01' ",
        "x": 230,
        "y": 120,
        "wires": [
            [
                "79d43421fe57dce5"
            ]
        ]
    },
    {
        "id": "79d43421fe57dce5",
        "type": "mysql",
        "z": "53983908339b7857",
        "mydb": "3564bcf07c743fdf",
        "name": "ptsapi",
        "x": 390,
        "y": 120,
        "wires": [
            [
                "32596e6e7a7a1bca"
            ]
        ]
    },
    {
        "id": "32596e6e7a7a1bca",
        "type": "function",
        "z": "53983908339b7857",
        "name": "get tickers",
        "func": "let tickers = ''\nlet item = 1;\n\nfor (let item of msg.payload) {\n    let ticker = item.ticker;\n    tickers += ticker+ \", \"\n}\n\nmsg.tickers = tickers\nnode.warn(tickers)\nreturn msg;",
        "outputs": 1,
        "noerr": 0,
        "initialize": "",
        "finalize": "",
        "libs": [],
        "x": 530,
        "y": 120,
        "wires": [
            [
                "d2c295e1cb0c8564"
            ]
        ]
    },
    {
        "id": "d2c295e1cb0c8564",
        "type": "change",
        "z": "53983908339b7857",
        "name": "",
        "rules": [
            {
                "t": "set",
                "p": "tickers",
                "pt": "flow",
                "to": "tickers",
                "tot": "msg"
            }
        ],
        "action": "",
        "property": "",
        "from": "",
        "to": "",
        "reg": false,
        "x": 700,
        "y": 120,
        "wires": [
            []
        ]
    },
    {
        "id": "3564bcf07c743fdf",
        "type": "MySQLdatabase",
        "name": "ptsapi",
        "host": "ptsapi.cax8fspskl8t.us-east-1.rds.amazonaws.com",
        "port": "3306",
        "db": "ptsapi",
        "tz": "EST5EDT",
        "charset": "UTF8"
    },
    {
        "id": "7455395cf269fb2b",
        "type": "postgreSQLConfig",
        "name": "",
        "host": "127.0.0.1",
        "hostFieldType": "str",
        "port": "5432",
        "portFieldType": "num",
        "database": "postgres",
        "databaseFieldType": "str",
        "ssl": "false",
        "sslFieldType": "bool",
        "applicationName": "",
        "applicationNameType": "str",
        "max": "10",
        "maxFieldType": "num",
        "idle": "1000",
        "idleFieldType": "num",
        "connectionTimeout": "10000",
        "connectionTimeoutFieldType": "num",
        "user": "docker",
        "userFieldType": "str",
        "password": "docker",
        "passwordFieldType": "str"
    },
    {
        "id": "651f0aab10dc1632",
        "type": "polygon-account",
        "name": "Polygon Key"
    },
    {
        "id": "e535f42f1df1b25f",
        "type": "alpaca-account",
        "name": "paper",
        "keyId": "PK4TI6GDJ7NN146CF8YA",
        "paper": true
    }
]